synthesizer/__init__.py
synthesizer/config/__init__.py
synthesizer/config/generation_settings/textbook_generation_settings.yaml
synthesizer/config/prompts/answer_question.yaml
synthesizer/config/prompts/chain_of_thought.yaml
synthesizer/core/__init__.py
synthesizer/core/base.py
synthesizer/core/prompt/__init__.py
synthesizer/core/prompt/base.py
synthesizer/core/utils.py
synthesizer/core/writers/__init__.py
synthesizer/core/writers/base.py
synthesizer/core/writers/jsonl_writer.py
synthesizer/core/writers/raw_writer.py
synthesizer/data/evals/science_multiple_choice.csv
synthesizer/data/sample/table_of_contents/Aerodynamics_of_Viscous_Fluids.yaml
synthesizer/data/sample/textbooks/Aerodynamics_of_Viscous_Fluids.md
synthesizer/eval/__init__.py
synthesizer/eval/base.py
synthesizer/eval/rag/__init__.py
synthesizer/eval/rag/science_multiple_choice/rag_science_evaluator.py
synthesizer/interface/__init__.py
synthesizer/interface/base.py
synthesizer/interface/llm/__init__.py
synthesizer/interface/llm/anthropic_interface.py
synthesizer/interface/llm/hugging_face_interface.py
synthesizer/interface/llm/openai_interface.py
synthesizer/interface/llm/sciphi_interface.py
synthesizer/interface/llm/vllm_interface.py
synthesizer/interface/llm_interface_manager.py
synthesizer/interface/rag/__init__.py
synthesizer/interface/rag/agent_search.py
synthesizer/interface/rag/bing_search/__init__.py
synthesizer/interface/rag/bing_search/base.py
synthesizer/interface/rag/bing_search/bing_client.py
synthesizer/interface/rag/bing_search/bing_types.py
synthesizer/interface/rag/local.py
synthesizer/interface/rag/serp_api.py
synthesizer/interface/rag_interface_manager.py
synthesizer/llm/__init__.py
synthesizer/llm/base.py
synthesizer/llm/config_manager.py
synthesizer/llm/models/__init__.py
synthesizer/llm/models/anthropic_llm.py
synthesizer/llm/models/hugging_face_llm.py
synthesizer/llm/models/openai_llm.py
synthesizer/llm/models/sciphi_llm.py
synthesizer/llm/models/vllm_llm.py
sciphi_synthesizer-1.0.5.dist-info/LICENSE
sciphi_synthesizer-1.0.5.dist-info/METADATA
sciphi_synthesizer-1.0.5.dist-info/WHEEL
sciphi_synthesizer-1.0.5.dist-info/RECORD
