Metadata-Version: 2.1
Name: sciphi-synthesizer
Version: 1.0.5
Summary: Synthesizer: A Framework for LLM Powered Data.
License: Apache-2.0
Author: Owen Colegrove
Author-email: owen@sciphi.ai
Requires-Python: >=3.9,<3.12
Classifier: License :: OSI Approved :: Apache Software License
Classifier: Programming Language :: Python :: 3
Classifier: Programming Language :: Python :: 3.9
Classifier: Programming Language :: Python :: 3.10
Classifier: Programming Language :: Python :: 3.11
Provides-Extra: all
Provides-Extra: all-with-extras
Provides-Extra: anthropic-support
Provides-Extra: hf-support
Provides-Extra: vllm-support
Requires-Dist: fire (>=0.5.0,<0.6.0)
Requires-Dist: pyyaml (>=6.0.1,<7.0.0)
Requires-Dist: retrying (>=1.3.4,<2.0.0)
